nlsam-1.0.dist-info/RECORD
nlsam-1.0.dist-info/WHEEL
nlsam-1.0.dist-info/entry_points.txt
nlsam-1.0.dist-info/top_level.txt
nlsam-1.0.dist-info/METADATA
nlsam-1.0.dist-info/licenses/LICENSE
nlsam/utils.cpython-312-darwin.so
nlsam/stabilizer.pyx
nlsam/__init__.py
nlsam/denoiser.py
nlsam/bias_correction.py
nlsam/angular_tools.py
nlsam/smoothing.py
nlsam/script.py
nlsam/stabilizer.cpython-312-darwin.so
nlsam/utils.pyx
nlsam/tests/test_smoothing.py
nlsam/tests/test_bias_correction.py
nlsam/tests/test_stabilizer.py
nlsam/tests/__init__.py
nlsam/tests/test_reshaping.py
nlsam/tests/test_angular_tools.py
nlsam/tests/test_main.py
nlsam/tests/datasets/bvals
nlsam/tests/datasets/noise.nii.gz
nlsam/tests/datasets/dwi_crop.nii.gz
nlsam/tests/datasets/bvecs
nlsam/tests/datasets/mask_crop.nii.gz
