Metadata-Version: 2.4
Name: nlsam
Version: 1.0
Summary: Implementation of "Non Local Spatial and Angular Matching : Enabling higher spatial resolution diffusion MRI datasets through adaptive denoising"
Author: Samuel St-Jean
License-Expression: GPL-3.0-or-later
Project-URL: homepage, https://github.com/samuelstjean/nlsam
Project-URL: documentation, https://nlsam.readthedocs.io/en/latest/
Project-URL: changelog, https://github.com/samuelstjean/nlsam/blob/master/CHANGELOG.md
Keywords: MRI,diffusion,dmri,denoising
Requires-Python: >=3.9
License-File: LICENSE
Requires-Dist: numpy>=1.21.3
Requires-Dist: scipy>=1.5
Requires-Dist: nibabel>=4.0
Requires-Dist: joblib>=1.3.0
Requires-Dist: autodmri>=0.2.1
Requires-Dist: spams-bin>=2.6.12
Requires-Dist: tqdm>=4.56
Dynamic: license-file
